setup.py
tezos_hd_util.egg-info/PKG-INFO
tezos_hd_util.egg-info/SOURCES.txt
tezos_hd_util.egg-info/dependency_links.txt
tezos_hd_util.egg-info/requires.txt
tezos_hd_util.egg-info/top_level.txt
tezoshd/__init__.py
tezoshd/tezoshd.py