Metadata-Version: 1.2
Name: tezos-hd-util
Version: 0.1.7
Summary: Python tool for for tezos hd generation
Home-page: https://github.com/oskyk/tezos-hd-util
Author: Oskar Hladky
Author-email: oskyks1@gmail.com
License: UNKNOWN
Download-URL: https://github.com/oskyk/tezos-hd-util/archive/0.1.6.tar.gz
Keywords: tezos,hd,address
Platform: UNKNOWN
Classifier: Programming Language :: Python :: 3
Classifier: Programming Language :: Python :: 3.6
Requires-Python: >=3
